node_hermes_core/__init__.py
node_hermes_core/cli.py
node_hermes_core/config_loader.py
node_hermes_core/loader.py
node_hermes_core/built_in/operation_nodes/__init__.py
node_hermes_core/built_in/operation_nodes/aggregator_node.py
node_hermes_core/built_in/operation_nodes/reference_node.py
node_hermes_core/built_in/output/__init__.py
node_hermes_core/built_in/output/simple_print.py
node_hermes_core/built_in/output/single_line_print.py
node_hermes_core/built_in/test_nodes/__init__.py
node_hermes_core/built_in/test_nodes/batch_sine.py
node_hermes_core/built_in/test_nodes/noise.py
node_hermes_core/built_in/test_nodes/print_output.py
node_hermes_core/built_in/test_nodes/raise_error.py
node_hermes_core/built_in/test_nodes/sine.py
node_hermes_core/data/__init__.py
node_hermes_core/data/datatypes.py
node_hermes_core/depencency/__init__.py
node_hermes_core/depencency/node_dependency.py
node_hermes_core/links/__init__.py
node_hermes_core/links/generic_link.py
node_hermes_core/links/queued_link.py
node_hermes_core/nodes/__init__.py
node_hermes_core/nodes/data_generator_node.py
node_hermes_core/nodes/depedency.py
node_hermes_core/nodes/generic_node.py
node_hermes_core/nodes/root_nodes.py
node_hermes_core/nodes/sink_node.py
node_hermes_core/nodes/source_node.py
node_hermes_core/objs/managed_task.py
node_hermes_core/objs/node_dependency.py
node_hermes_core/objs/signal.py
node_hermes_core/utils/frequency_counter.py
node_hermes_core/utils/log_setup.py
node_hermes_core-1.3.1.dist-info/METADATA
node_hermes_core-1.3.1.dist-info/WHEEL
node_hermes_core-1.3.1.dist-info/entry_points.txt
node_hermes_core-1.3.1.dist-info/RECORD
