Metadata-Version: 2.4
Name: node-hermes-core
Version: 1.3.1
Summary: Core libary for the Node Hermes project.
Author-email: floris vernieuwe <floris@vernieuwe.eu>
Requires-Python: >=3.10
Requires-Dist: numpy>=2.2.3
Requires-Dist: polars>=1.23.0
Requires-Dist: pydantic-yaml>=1.4.0
Requires-Dist: pydantic>=2.10.6
